i2plib/__init__.py
i2plib/__version__.py
i2plib/aiosam.py
i2plib/exceptions.py
i2plib/log.py
i2plib/sam.py
i2plib/tunnel.py
i2plib/utils.py
i2plib-0.0.14.dist-info/METADATA
i2plib-0.0.14.dist-info/RECORD
i2plib-0.0.14.dist-info/WHEEL
i2plib-0.0.14.dist-info/top_level.txt
