Metadata-Version: 2.1
Name: i2plib
Version: 0.0.14
Summary: A modern asynchronous library for building I2P applications.
Home-page: https://github.com/l-n-s/i2plib
Author: Viktor Villainov
Author-email: supervillain@riseup.net
License: MIT
Keywords: i2p
Platform: UNKNOWN
Classifier: Development Status :: 4 - Beta
Classifier: License :: OSI Approved :: MIT License
Classifier: Programming Language :: Python :: 3.5
Classifier: Programming Language :: Python :: 3.6
Classifier: Programming Language :: Python :: 3.7
